erkCalc/EMath.py
erkCalc/PrintArea.py
erkCalc/__init__.py
erkCalc/setup.py
pyAreaSampleTrial-1.0.dist-info/License.txt
pyAreaSampleTrial-1.0.dist-info/METADATA
pyAreaSampleTrial-1.0.dist-info/WHEEL
pyAreaSampleTrial-1.0.dist-info/top_level.txt
pyAreaSampleTrial-1.0.dist-info/RECORD
