Metadata-Version: 2.1
Name: pyAreaSampleTrial
Version: 1.0
Summary: Trial Package
Home-page: 
Author: erdal.kilinc
Author-email: erkilinc@gmail.com
License: MIT
License-File: License.txt
